checkmk-commander/__init__.py
checkmk_commander-0.8.13.data/data/share/applications/checkmk-commander.desktop
checkmk_commander-0.8.13.data/data/share/icons/hicolor/256x256/apps/checkmk-commander.png
checkmk_commander-0.8.13.data/data/share/icons/hicolor/48x48/apps/checkmk-commander.png
checkmk_commander-0.8.13.data/scripts/chkcom
checkmkcommander/__init__.py
checkmkcommander/command_line.py
checkmkcommander/tests/__init__.py
checkmk_commander-0.8.13.dist-info/LICENSE
checkmk_commander-0.8.13.dist-info/METADATA
checkmk_commander-0.8.13.dist-info/WHEEL
checkmk_commander-0.8.13.dist-info/top_level.txt
checkmk_commander-0.8.13.dist-info/RECORD
