Metadata-Version: 2.1
Name: checkmk-commander
Version: 0.8.13
Summary: Curses interface to Checkmk Raw.
Home-page: https://gitlab.com/larsfp/checkmk-commander
Author: Lars Falk-Petersen
Author-email: dev@falkp.no
License: GPLv3+
Keywords: monitoring
Platform: UNKNOWN
Classifier: Development Status :: 4 - Beta
Classifier: Intended Audience :: System Administrators
Classifier: License :: OSI Approved :: GNU General Public License v3 or later (GPLv3+)
Classifier: Programming Language :: Python :: 3
Classifier: Programming Language :: Python :: 3.6
Classifier: Programming Language :: Python :: 3.7
Classifier: Programming Language :: Python :: 3.8
Classifier: Topic :: System :: Networking
Classifier: Environment :: Console :: Curses
Classifier: Operating System :: POSIX :: Linux
Classifier: Environment :: Console
Classifier: Topic :: System :: Networking :: Monitoring
Requires-Python: >=3.6
Requires-Dist: urwid
Requires-Dist: requests
Requires-Dist: appdirs
Requires-Dist: wheel
